{
  "format": "page",
  "id": "ourcaremanagementsolutions",
  "label": "ourcaremanagementsolutions",
  "repeatable": false,
  "status": true,
  "json": {
    "Main": {
      "headerbackground": {
        "type": "Image",
        "config": {
          "label": "headerbackground",
          "constraint": {},
          "thumbnails": []
        }
      },
      "headertext": {
        "type": "Text",
        "config": {
          "label": "headertext",
          "placeholder": ""
        }
      },
      "content": {
        "type": "Text",
        "config": {
          "label": "content",
          "placeholder": ""
        }
      },
      "leftheader": {
        "type": "Text",
        "config": {
          "label": "leftheader",
          "placeholder": ""
        }
      },
      "leftcontent": {
        "type": "Text",
        "config": {
          "label": "leftcontent",
          "placeholder": ""
        }
      },
      "buttontext": {
        "type": "Text",
        "config": {
          "label": "buttontext",
          "placeholder": ""
        }
      },
      "rightimage": {
        "type": "Image",
        "config": {
          "label": "rightimage",
          "constraint": {},
          "thumbnails": []
        }
      },
      "buttonimage": {
        "type": "Image",
        "config": {
          "label": "buttonimage",
          "constraint": {},
          "thumbnails": []
        }
      },
      "leafimageleft": {
        "type": "Image",
        "config": {
          "label": "leafimageleft",
          "constraint": {},
          "thumbnails": []
        }
      },
      "leafimageright": {
        "type": "Image",
        "config": {
          "label": "leafimageright",
          "constraint": {},
          "thumbnails": []
        }
      },
      "pieimage": {
        "type": "Image",
        "config": {
          "label": "pieimage",
          "constraint": {},
          "thumbnails": []
        }
      },
      "pietext": {
        "type": "Text",
        "config": {
          "label": "pietext",
          "placeholder": ""
        }
      },
      "rightleaftextheader": {
        "type": "Text",
        "config": {
          "label": "rightleaftextheader",
          "placeholder": ""
        }
      },
      "rightleaftextcontent": {
        "type": "Text",
        "config": {
          "label": "rightleaftextcontent",
          "placeholder": ""
        }
      },
      "rightleafdowntextheader": {
        "type": "Text",
        "config": {
          "label": "rightleafdowntextheader",
          "placeholder": ""
        }
      },
      "rightleafdowntextcontent": {
        "type": "Text",
        "config": {
          "label": "rightleafdowntextcontent",
          "placeholder": ""
        }
      },
      "pielefttext": {
        "type": "Text",
        "config": {
          "label": "pielefttext",
          "placeholder": ""
        }
      },
      "leafsectionheader": {
        "type": "Text",
        "config": {
          "label": "leafsectionheader",
          "placeholder": ""
        }
      },
      "leafsectioncontent": {
        "type": "Text",
        "config": {
          "label": "leafsectioncontent",
          "placeholder": ""
        }
      },
      "heading1": {
        "type": "Text",
        "config": {
          "label": "Heading1",
          "placeholder": ""
        }
      },
      "heading1_point1": {
        "type": "Text",
        "config": {
          "label": "Heading1 Point1",
          "placeholder": ""
        }
      },
      "heading1_point2": {
        "type": "Text",
        "config": {
          "label": "Heading1 Point2",
          "placeholder": ""
        }
      },
      "heading2": {
        "type": "Text",
        "config": {
          "label": "Heading2",
          "placeholder": ""
        }
      },
      "heading2_point1": {
        "type": "Text",
        "config": {
          "label": "Heading2 Point1",
          "placeholder": ""
        }
      },
      "heading2_point2": {
        "type": "Text",
        "config": {
          "label": "Heading2 Point2",
          "placeholder": ""
        }
      },
      "heading3": {
        "type": "Text",
        "config": {
          "label": "Heading3",
          "placeholder": ""
        }
      },
      "heading3_point1": {
        "type": "Text",
        "config": {
          "label": "Heading3 Point1",
          "placeholder": ""
        }
      },
      "heading3_point2": {
        "type": "Text",
        "config": {
          "label": "Heading3 Point2",
          "placeholder": ""
        }
      },
      "heading4": {
        "type": "Text",
        "config": {
          "label": "Heading4",
          "placeholder": ""
        }
      },
      "heading4_point1": {
        "type": "Text",
        "config": {
          "label": "Heading4 Point1",
          "placeholder": ""
        }
      },
      "heading4_point2": {
        "type": "Text",
        "config": {
          "label": "Heading4 Point2",
          "placeholder": ""
        }
      },
      "heading5": {
        "type": "Text",
        "config": {
          "label": "Heading5",
          "placeholder": ""
        }
      },
      "heading5_point1": {
        "type": "Text",
        "config": {
          "label": "Heading5 Point1",
          "placeholder": ""
        }
      },
      "heading5_point2": {
        "type": "Text",
        "config": {
          "label": "Heading5 Point2",
          "placeholder": ""
        }
      },
      "heading5_point3": {
        "type": "Text",
        "config": {
          "label": "Heading5 Point3",
          "placeholder": ""
        }
      },
      "heading6": {
        "type": "Text",
        "config": {
          "label": "Heading6",
          "placeholder": ""
        }
      },
      "heading6_point1": {
        "type": "Text",
        "config": {
          "label": "Heading6 Point1",
          "placeholder": ""
        }
      },
      "heading6_point2": {
        "type": "Text",
        "config": {
          "label": "Heading6 Point2",
          "placeholder": ""
        }
      },
      "heading7": {
        "type": "Text",
        "config": {
          "label": "Heading7",
          "placeholder": ""
        }
      },
      "heading7_point1": {
        "type": "Text",
        "config": {
          "label": "Heading7 Point1",
          "placeholder": ""
        }
      },
      "heading7_point2": {
        "type": "Text",
        "config": {
          "label": "Heading7 Point2",
          "placeholder": ""
        }
      },
      "heading8": {
        "type": "Text",
        "config": {
          "label": "Heading8",
          "placeholder": ""
        }
      },
      "heading8_point1": {
        "type": "Text",
        "config": {
          "label": "Heading8 Point1",
          "placeholder": ""
        }
      },
      "heading8_point2": {
        "type": "Text",
        "config": {
          "label": "Heading8 Point2",
          "placeholder": ""
        }
      },
      "slices": {
        "type": "Slices",
        "fieldset": "Slice Zone",
        "config": {
          "choices": {}
        }
      }
    },
    "SEO & Metadata": {
      "meta_title": {
        "config": {
          "label": "Meta Title",
          "placeholder": "A title of the page used for social media and search engines"
        },
        "type": "Text"
      },
      "meta_description": {
        "config": {
          "label": "Meta Description",
          "placeholder": "A brief summary of the page"
        },
        "type": "Text"
      },
      "meta_image": {
        "config": {
          "constraint": {
            "height": 1260,
            "width": 2400
          },
          "label": "Meta Image",
          "thumbnails": []
        },
        "type": "Image"
      }
    }
  }
}
